arcaverborum/__init__.py
arcaverborum/common.py
arcaverborum/sampling.py
arcaverborum/etc/gled_global.dst
arcaverborum/etc/haversine.tsv.gz
arcaverborum-0.2.1.dist-info/AUTHORS.md
arcaverborum-0.2.1.dist-info/LICENSE
arcaverborum-0.2.1.dist-info/METADATA
arcaverborum-0.2.1.dist-info/WHEEL
arcaverborum-0.2.1.dist-info/top_level.txt
arcaverborum-0.2.1.dist-info/RECORD
